Metadata-Version: 1.0
Name: spamlib
Version: 0.0.1
Summary: Simple library to spam
Home-page: UNKNOWN
Author: UNKNOWN
Author-email: asimonov1998@gmail.com
License: UNKNOWN
Platform: UNKNOWN
